bjorn/__init__.py
bjorn/config.py
bjorn-0.1.5.dist-info/AUTHORS.rst
bjorn-0.1.5.dist-info/LICENSE
bjorn-0.1.5.dist-info/METADATA
bjorn-0.1.5.dist-info/WHEEL
bjorn-0.1.5.dist-info/top_level.txt
bjorn-0.1.5.dist-info/RECORD
