Metadata-Version: 2.1
Name: bjorn
Version: 0.1.5
Summary: It loads different configurations depending on the environment variable.
Home-page: https://github.com/juanmcristobal/bjorn
Author: Juan Manuel Cristóbal Moreno
Author-email: juanmcristobal@gmail.com
License: MIT license
Keywords: bjorn
Classifier: Development Status :: 2 - Pre-Alpha
Classifier: Intended Audience :: Developers
Classifier: License :: OSI Approved :: MIT License
Classifier: Natural Language :: English
Classifier: Programming Language :: Python :: 3
Classifier: Programming Language :: Python :: 3.6
Classifier: Programming Language :: Python :: 3.7
Classifier: Programming Language :: Python :: 3.8
Classifier: Programming Language :: Python :: 3.9
Classifier: Programming Language :: Python :: 3.10
Classifier: Programming Language :: Python :: 3.11
Requires-Python: >=3.5
License-File: LICENSE
License-File: AUTHORS.rst
